caffeine/__init__.py
caffeine/__main__.py
caffeine/modules/__init__.py
caffeine/modules/exceptions.py
caffeine/modules/optimize.py
caffeine/modules/operators/__init__.py
caffeine/modules/operators/fileio.py
caffeine/modules/operators/internal.py
caffeine/modules/operators/math.py
caffeine/modules/operators/objects.py
caffeine/modules/operators/stdio.py
caffeine/modules/operators/strman.py
xpp/__init__.py
xpp/__main__.py
xpp/exceptions.py
xpp/core/datastore.py
xpp/core/interpreter.py
xpp/core/sections.py
xpp/core/tokenizer.py
xpp/extra/config.py
xpp/modules/simpleeval.py
xpp/modules/ops/__init__.py
xpp/modules/ops/shared.py
xpp/modules/ops/stdlib/fileio.py
xpp/modules/ops/stdlib/import_.py
xpp/modules/ops/stdlib/internal.py
xpp/modules/ops/stdlib/math.py
xpp/modules/ops/stdlib/objects.py
xpp/modules/ops/stdlib/stdio.py
xpp/modules/ops/stdlib/strman.py
xpp-3.1.3.dist-info/METADATA
xpp-3.1.3.dist-info/WHEEL
xpp-3.1.3.dist-info/entry_points.txt
xpp-3.1.3.dist-info/licenses/LICENSE.txt
xpp-3.1.3.dist-info/RECORD
