Metadata-Version: 2.3
Name: xpp
Version: 3.1.3
Summary: The x++ programming language.
Project-URL: Bug Reports, https://github.com/iiPythonx/xpp/issues
Project-URL: Homepage, https://github.com/iiPythonx/xpp
Project-URL: Source, https://github.com/iiPythonx/xpp
Author-email: iiPython <ben@iipython.dev>
License: MIT
Keywords: interpreter,language,parser,xpp
Classifier: Development Status :: 5 - Production/Stable
Classifier: Environment :: Console
Classifier: Intended Audience :: Developers
Classifier: Intended Audience :: Education
Classifier: License :: OSI Approved :: MIT License
Classifier: Operating System :: OS Independent
Classifier: Programming Language :: Python :: 3.10
Classifier: Topic :: Education
Classifier: Topic :: Software Development
Classifier: Topic :: Software Development :: Interpreters
Requires-Python: <4,>=3.10
Provides-Extra: tests
Requires-Dist: rich; extra == 'tests'
